LICENSE
MANIFEST.in
README.md
pyproject.toml
setup.py
version.py
csrc/bind.cc
csrc/embedding/adam.cc
csrc/embedding/adamw.cc
csrc/embedding/adamw_tf.cc
csrc/embedding/children_info.cc
csrc/embedding/cpu_id_map.cc
csrc/embedding/gpu_id_map.cu
csrc/embedding/hashtable.cc
csrc/embedding/id_allocator.cc
csrc/embedding/initializer.cc
csrc/embedding/optim.cc
csrc/embedding/parallel_util.cc
csrc/embedding/slice_info.cc
csrc/embedding/slot_group.cc
csrc/ops/adam_tf_op.cc
csrc/ops/adam_tf_op_kernel.cu
csrc/ops/block_apply_adamw_op.cc
csrc/ops/block_apply_adamw_op_kernel.cu
csrc/ops/block_ops.cc
csrc/ops/block_ops_kernel.cu
csrc/ops/bucketize_op.cc
csrc/ops/bucketize_op_kernel.cu
csrc/ops/calc_ragged_index.cc
csrc/ops/dense_to_ragged.cc
csrc/ops/dense_to_ragged_kernel.cu
csrc/ops/embedding_segment_reduce_kernel.cu
csrc/ops/feature_cross_ragged.cc
csrc/ops/feature_cross_ragged_kernel.cu
csrc/ops/fused_bucketized.cc
csrc/ops/fused_bucketized_kernel.cu
csrc/ops/fused_hash.cc
csrc/ops/fused_hash_kernel.cu
csrc/ops/fused_ragged_cutoff.cc
csrc/ops/fused_ragged_cutoff_kernel.cu
csrc/ops/fused_uint64_mod.cc
csrc/ops/fused_uint64_mod_kernel.cu
csrc/ops/gauc.cc
csrc/ops/hashtable_ops.cc
csrc/ops/hashtable_ops_kernel.cu
csrc/ops/ids_encode.cc
csrc/ops/ids_encode_kernel.cu
csrc/ops/ids_partition.cc
csrc/ops/ids_partition_kernel.cu
csrc/ops/multi_hash.cc
csrc/ops/multi_hash_kernel.cu
csrc/ops/ragged_tile_kernel.cu
csrc/ops/ragged_to_dense.cc
csrc/ops/ragged_to_dense_kernel.cu
csrc/ops/ragged_to_sparse.cc
csrc/ops/segment_ops.cc
csrc/ops/segment_ops_kernel.cu
csrc/ops/uint64_mod.cc
csrc/ops/uint64_mod_kernel.cu
csrc/platform/env.cc
csrc/platform/file_system_helper.cc
csrc/platform/fileoutput_buffer.cc
csrc/platform/filesystem.cc
csrc/platform/path.cc
csrc/platform/status.cc
csrc/platform/posix/env.cc
csrc/platform/posix/posix_filesystem.cc
csrc/serialize/block_info.cc
csrc/serialize/checkpoint_reader.cc
csrc/serialize/dtype_serialize.cc
csrc/serialize/ht_read_collection.cc
recis_gpu.egg-info/PKG-INFO
recis_gpu.egg-info/SOURCES.txt
recis_gpu.egg-info/dependency_links.txt
recis_gpu.egg-info/not-zip-safe
recis_gpu.egg-info/requires.txt
recis_gpu.egg-info/top_level.txt